pr_checker_ai/__init__.py
pr_checker_ai/gh.py
pr_checker_ai/main.py
pr_checker_ai/utils.py
pr_checker_ai-0.1.0.dist-info/METADATA
pr_checker_ai-0.1.0.dist-info/WHEEL
pr_checker_ai-0.1.0.dist-info/entry_points.txt
pr_checker_ai-0.1.0.dist-info/licenses/LICENSE
pr_checker_ai-0.1.0.dist-info/RECORD
