Metadata-Version: 2.4
Name: pr-checker-ai
Version: 0.1.0
Summary: Add your description here
License-File: LICENSE
Requires-Python: >=3.11
Requires-Dist: anthropic>=0.61.0
Requires-Dist: openai>=1.99.2
Requires-Dist: pydantic>=2.11.7
Requires-Dist: rich>=14.1.0
